{ 
    "Top10TVshows" :[
    {
        "id": 1,
        "title": "The Morning Show",
        "genre": "TV Show",
        "type": "Nonfiction",
        "year": 2023,
        "url": "https://tv.apple.com/show/umc.cmc.3344556677",
        "poster": "https://is1-ssl.mzstatic.com/image/thumb/Yb3h7gN9sCd6czLGOU4Ikg/580x326.webp"
    },
    {
        "id": 2,
       "title": "Platonic",
        "genre": "Comedies",
        "type": "Nonfiction",
        "year": 2023,
        "url": "https://tv.apple.com/show/umc.cmc.0011223344",
        "poster": "https://is1-ssl.mzstatic.com/image/thumb/rBI93Qq60YpBP60maTBNbg/580x326.webp"
    },
    {
        "id": 3,
        "title": "The Studio",
        "type": "Nonfiction",
        "year": 2023,
        "genre": "Comedies",
        "url": "https://tv.apple.com/show/umc.cmc.6677889900",
        "poster": "https://is1-ssl.mzstatic.com/image/thumb/5geoozRQUAjDnWF2KLHyJg/580x326.webp"
    },
    {
        "id": 4,
        "title": "Chief of War",
        "genre": "Dramas",
        "type": "Nonfiction",
        "year": 2023,
        "url": "https://tv.apple.com/show/umc.cmc.4455667788",
        "poster": "https://is1-ssl.mzstatic.com/image/thumb/twLCcLLXmcLBqEf3Af3vww/580x326.webp"
    },
    {
        "id": 5,
        "title": "Invasion",
        "type": "Nonfiction",
        "year": 2023,
        "genre": "Sci-Fi",
        "url": "https://tv.apple.com/show/umc.cmc.5566778899",
        "poster": "https://is1-ssl.mzstatic.com/image/thumb/76HMwZ8974tWz_042k2vig/580x326.webp"
    },
    {
        "id": 6,
        "title": "Foundation",
        "genre": "Sci-Fi",
        "type": "Nonfiction",
        "year": 2023,
        "url": "https://tv.apple.com/show/umc.cmc.1122334455",
        "poster": "https://is1-ssl.mzstatic.com/image/thumb/Xye2zsX5gxLetoLRdTgNLA/580x326.webp"
    },
    {
        "id": 7,
        "title": "Severence",
        "genre": "Thriller",
        "type": "Nonfiction",
        "year": 2023,
        "url": "https://tv.apple.com/show/umc.cmc.7788990011",
        "poster": "https://is1-ssl.mzstatic.com/image/thumb/EUeDAPovZrBtOcrP2Da5Lw/580x326.webp"
    },
    {
        "id": 8,
        "title": "Acapulco",
        "type": "Nonfiction",
        "year": 2023,
        "genre": "Comedies",
        "url": "https://tv.apple.com/show/umc.cmc.8899001122",
        "poster": "https://is1-ssl.mzstatic.com/image/thumb/Ec4GedDwtKAxOrCp_VOF-g/580x326.webp"
    },
    {
        "id": 9,
        "title": "Slow Horses",
        "type": "Nonfiction",
        "year": 2023,
        "genre": "Thriller",
        "url": "https://tv.apple.com/show/umc.cmc.9900112233",
        "poster": "https://is1-ssl.mzstatic.com/image/thumb/S2T1FMcov5a0GzmninlU4Q/580x326.webp"
    },
    {
        "id": 10,
        "title": "Ted Lasso",
        "genre": "TV Show",
        "type": "Nonfiction",
        "year": 2023,
        "url": "https://tv.apple.com/show/umc.cmc.2233445566",
        "poster": "https://is1-ssl.mzstatic.com/image/thumb/ageP1PYyLi7UlNiWMva32Q/580x326.webp"
        
    }
]
}